{
    "boxShadow": "{{appsmith.theme.boxShadow.appBoxShadow}}",
    "mobileBottomRow": 38,
    "widgetName": "Iframe1",
    "srcDoc": "{{JSObject1.myFun1()}}",
    "dynamicPropertyPathList": [],
    "displayName": "Iframe",
    "iconSVG": "https://appcdn.appsmith.com/static/media/icon.a84667dbdc548d14f7c83df551151550.svg",
    "searchTags": ["embed"],
    "topRow": 4,
    "bottomRow": 47,
    "parentRowSpace": 10,
    "source": "https://www.example.com",
    "type": "IFRAME_WIDGET",
    "hideCard": false,
    "mobileRightColumn": 28,
    "borderOpacity": 100,
    "animateLoading": true,
    "parentColumnSpace": 6.9375,
    "dynamicTriggerPathList": [],
    "leftColumn": 2,
    "dynamicBindingPathList": [
        {"key": "borderRadius"},
        {"key": "boxShadow"},
        {"key": "srcDoc"}
    ],
    "borderWidth": 1,
    "flexVerticalAlignment": "start",
    "key": "9n4nx015xo",
    "isDeprecated": false,
    "rightColumn": 62,
    "widgetId": "n37evzvpgw",
    "isVisible": true,
    "version": 1,
    "parentId": "732d7zmipm",
    "tags": ["Display"],
    "renderMode": "CANVAS",
    "isLoading": false,
    "mobileTopRow": 6,
    "responsiveBehavior": "fill",
    "borderRadius": "{{appsmith.theme.borderRadius.appBorderRadius}}",
    "mobileLeftColumn": 4,
    "onSrcDocChanged": "{{}}"
}